coininfo_Sahel/__init__.py
coininfo_Sahel/info.py
coininfo_sahel-0.1.2.dist-info/METADATA
coininfo_sahel-0.1.2.dist-info/WHEEL
coininfo_sahel-0.1.2.dist-info/top_level.txt
coininfo_sahel-0.1.2.dist-info/RECORD
