Metadata-Version: 2.1
Name: coininfo-sahel
Version: 0.1.2
Requires-Dist: requests ==2.31.0
